pgrid/__init__.py
pgrid-1.0.dist-info/LICENCE.txt
pgrid-1.0.dist-info/METADATA
pgrid-1.0.dist-info/WHEEL
pgrid-1.0.dist-info/top_level.txt
pgrid-1.0.dist-info/RECORD
